llamasearch_experimentalagents_product_growth/__init__.py
llamasearch_experimentalagents_product_growth/cli.py
llamasearch_experimentalagents_product_growth/agents/__init__.py
llamasearch_experimentalagents_product_growth/agents/analyzer.py
llamasearch_experimentalagents_product_growth/agents/strategist.py
llamasearch_experimentalagents_product_growth/core/__init__.py
llamasearch_experimentalagents_product_growth/core/knowledge_base.py
llamasearch_experimentalagents_product_growth/core/llm.py
llamasearch_experimentalagents_product_growth/core/llm_client.py
llamasearch_experimentalagents_product_growth/core/llm_router.py
llamasearch_experimentalagents_product_growth/integrations/__init__.py
llamasearch_experimentalagents_product_growth/models/__init__.py
llamasearch_experimentalagents_product_growth/models/feedback.py
llamasearch_experimentalagents_product_growth/models/strategy.py
llamasearch_experimentalagents_product_growth/utils/__init__.py
llamasearch_experimentalagents_product_growth-0.1.0.dist-info/METADATA
llamasearch_experimentalagents_product_growth-0.1.0.dist-info/WHEEL
llamasearch_experimentalagents_product_growth-0.1.0.dist-info/entry_points.txt
llamasearch_experimentalagents_product_growth-0.1.0.dist-info/licenses/LICENSE
llamasearch_experimentalagents_product_growth-0.1.0.dist-info/RECORD
