Metadata-Version: 2.4
Name: llamasearch-experimentalagents-product-growth
Version: 0.1.0
Summary: AI-powered product growth platform with multi-LLM support
Project-URL: Homepage, https://github.com/llamasearch/experimentalagents-product-growth
Project-URL: Documentation, https://llamasearch.github.io/experimentalagents-product-growth
Project-URL: Source, https://github.com/llamasearch/experimentalagents-product-growth
Project-URL: Bug Tracker, https://github.com/llamasearch/experimentalagents-product-growth/issues
Author-email: Nik Jois <nikjois@llamasearch.ai>
License: MIT
License-File: LICENSE
Classifier: Development Status :: 4 - Beta
Classifier: Intended Audience :: Developers
Classifier: License :: OSI Approved :: MIT License
Classifier: Programming Language :: Python :: 3
Classifier: Programming Language :: Python :: 3.10
Classifier: Programming Language :: Python :: 3.11
Classifier: Programming Language :: Python :: Implementation :: CPython
Classifier: Topic :: Scientific/Engineering :: Artificial Intelligence
Requires-Python: >=3.10
Requires-Dist: datasets>=2.12.0
Requires-Dist: datasette>=0.64.5
Requires-Dist: numpy>=1.24.0
Requires-Dist: openai>=1.0.0
Requires-Dist: pandas>=2.0.0
Requires-Dist: pydantic>=2.0.0
Requires-Dist: python-dotenv>=1.0.0
Requires-Dist: rich>=13.3.5
Requires-Dist: scikit-learn>=1.2.0
Requires-Dist: sqlite-utils>=3.35
Requires-Dist: tqdm>=4.65.0
Requires-Dist: typer>=0.9.0
Provides-Extra: all
Requires-Dist: anthropic>=0.5.0; extra == 'all'
Requires-Dist: black>=23.3.0; extra == 'all'
Requires-Dist: isort>=5.12.0; extra == 'all'
Requires-Dist: jax>=0.4.8; extra == 'all'
Requires-Dist: jaxlib>=0.4.7; extra == 'all'
Requires-Dist: llama-cpp-python>=0.1.77; extra == 'all'
Requires-Dist: mkdocs-material>=9.1.8; extra == 'all'
Requires-Dist: mkdocs>=1.4.3; extra == 'all'
Requires-Dist: mkdocstrings-python>=1.1.2; extra == 'all'
Requires-Dist: mkdocstrings>=0.21.2; extra == 'all'
Requires-Dist: mlx>=0.0.1; (sys_platform == 'darwin') and extra == 'all'
Requires-Dist: mypy>=1.2.0; extra == 'all'
Requires-Dist: pre-commit>=3.3.1; extra == 'all'
Requires-Dist: pytest-cov>=4.1.0; extra == 'all'
Requires-Dist: pytest-mock>=3.10.0; extra == 'all'
Requires-Dist: pytest>=7.3.1; extra == 'all'
Requires-Dist: ruff>=0.0.262; extra == 'all'
Provides-Extra: anthropic
Requires-Dist: anthropic>=0.5.0; extra == 'anthropic'
Provides-Extra: dev
Requires-Dist: black>=23.3.0; extra == 'dev'
Requires-Dist: isort>=5.12.0; extra == 'dev'
Requires-Dist: mypy>=1.2.0; extra == 'dev'
Requires-Dist: pre-commit>=3.3.1; extra == 'dev'
Requires-Dist: pytest-cov>=4.1.0; extra == 'dev'
Requires-Dist: pytest-mock>=3.10.0; extra == 'dev'
Requires-Dist: pytest>=7.3.1; extra == 'dev'
Requires-Dist: ruff>=0.0.262; extra == 'dev'
Provides-Extra: docs
Requires-Dist: mkdocs-material>=9.1.8; extra == 'docs'
Requires-Dist: mkdocs>=1.4.3; extra == 'docs'
Requires-Dist: mkdocstrings-python>=1.1.2; extra == 'docs'
Requires-Dist: mkdocstrings>=0.21.2; extra == 'docs'
Provides-Extra: jax
Requires-Dist: jax>=0.4.8; extra == 'jax'
Requires-Dist: jaxlib>=0.4.7; extra == 'jax'
Provides-Extra: local
Requires-Dist: llama-cpp-python>=0.1.77; extra == 'local'
Provides-Extra: mlx
Requires-Dist: mlx>=0.0.1; (sys_platform == 'darwin') and extra == 'mlx'
